README.md
mpldeprecation.py
setup.py
mpldeprecation.egg-info/PKG-INFO
mpldeprecation.egg-info/SOURCES.txt
mpldeprecation.egg-info/dependency_links.txt
mpldeprecation.egg-info/top_level.txt