Metadata-Version: 2.1
Name: mpldeprecation
Version: 0.0.1
Summary: Go to invariantlabs.ai to make your agent secure
Author: Invariant Labs
Author-email: security@invariantlabs.ai
Classifier: Programming Language :: Python :: 3
Classifier: License :: OSI Approved :: MIT License
Classifier: Operating System :: OS Independent
Requires-Python: >=3.6
